{
  "children": [
    {
      "children": [
        {
          "children": [
            {
              "children": [], 
              "name": "name", 
              "attrs": {}
            }
          ], 
          "name": "translator", 
          "attrs": {}
        }, 
        {
          "children": [], 
          "name": "rights", 
          "attrs": {
            "license": "http://creativecommons.org/licenses/by-sa/3.0/"
          }
        }, 
        {
          "children": [], 
          "name": "updated", 
          "attrs": {}
        }
      ], 
      "name": "info", 
      "attrs": {}
    }, 
    {
      "children": [], 
      "name": "style-options", 
      "attrs": {
        "punctuation-in-quote": "false"
      }
    }, 
    {
      "children": [
        {
          "children": [], 
          "name": "date-part", 
          "attrs": {
            "name": "day", 
            "suffix": " de "
          }
        }, 
        {
          "children": [], 
          "name": "date-part", 
          "attrs": {
            "name": "month", 
            "suffix": " de "
          }
        }, 
        {
          "children": [], 
          "name": "date-part", 
          "attrs": {
            "name": "year"
          }
        }
      ], 
      "name": "date", 
      "attrs": {
        "form": "text"
      }
    }, 
    {
      "children": [
        {
          "children": [], 
          "name": "date-part", 
          "attrs": {
            "name": "day", 
            "form": "numeric-leading-zeros", 
            "suffix": "/"
          }
        }, 
        {
          "children": [], 
          "name": "date-part", 
          "attrs": {
            "name": "month", 
            "form": "numeric-leading-zeros", 
            "suffix": "/"
          }
        }, 
        {
          "children": [], 
          "name": "date-part", 
          "attrs": {
            "name": "year"
          }
        }
      ], 
      "name": "date", 
      "attrs": {
        "form": "numeric"
      }
    }, 
    {
      "children": [
        {
          "children": [
            "accedido"
          ], 
          "name": "term", 
          "attrs": {
            "name": "accessed"
          }
        }, 
        {
          "children": [
            "y"
          ], 
          "name": "term", 
          "attrs": {
            "name": "and"
          }
        }, 
        {
          "children": [
            "y otros"
          ], 
          "name": "term", 
          "attrs": {
            "name": "and others"
          }
        }, 
        {
          "children": [
            "an\u00f3nimo"
          ], 
          "name": "term", 
          "attrs": {
            "name": "anonymous"
          }
        }, 
        {
          "children": [
            "an\u00f3n."
          ], 
          "name": "term", 
          "attrs": {
            "name": "anonymous", 
            "form": "short"
          }
        }, 
        {
          "children": [
            "en"
          ], 
          "name": "term", 
          "attrs": {
            "name": "at"
          }
        }, 
        {
          "children": [
            "disponible en"
          ], 
          "name": "term", 
          "attrs": {
            "name": "available at"
          }
        }, 
        {
          "children": [
            "de"
          ], 
          "name": "term", 
          "attrs": {
            "name": "by"
          }
        }, 
        {
          "children": [
            "circa"
          ], 
          "name": "term", 
          "attrs": {
            "name": "circa"
          }
        }, 
        {
          "children": [
            "c."
          ], 
          "name": "term", 
          "attrs": {
            "name": "circa", 
            "form": "short"
          }
        }, 
        {
          "children": [
            "citado"
          ], 
          "name": "term", 
          "attrs": {
            "name": "cited"
          }
        }, 
        {
          "children": [
            {
              "children": [
                "edici\u00f3n"
              ], 
              "name": "single", 
              "attrs": {}
            }, 
            {
              "children": [
                "ediciones"
              ], 
              "name": "multiple", 
              "attrs": {}
            }
          ], 
          "name": "term", 
          "attrs": {
            "name": "edition"
          }
        }, 
        {
          "children": [
            "ed."
          ], 
          "name": "term", 
          "attrs": {
            "name": "edition", 
            "form": "short"
          }
        }, 
        {
          "children": [
            "et\u00a0al."
          ], 
          "name": "term", 
          "attrs": {
            "name": "et-al"
          }
        }, 
        {
          "children": [
            "previsto"
          ], 
          "name": "term", 
          "attrs": {
            "name": "forthcoming"
          }
        }, 
        {
          "children": [
            "a partir de"
          ], 
          "name": "term", 
          "attrs": {
            "name": "from"
          }
        }, 
        {
          "children": [
            "ibid."
          ], 
          "name": "term", 
          "attrs": {
            "name": "ibid"
          }
        }, 
        {
          "children": [
            "en"
          ], 
          "name": "term", 
          "attrs": {
            "name": "in"
          }
        }, 
        {
          "children": [
            "en imprenta"
          ], 
          "name": "term", 
          "attrs": {
            "name": "in press"
          }
        }, 
        {
          "children": [
            "internet"
          ], 
          "name": "term", 
          "attrs": {
            "name": "internet"
          }
        }, 
        {
          "children": [
            "entrevista"
          ], 
          "name": "term", 
          "attrs": {
            "name": "interview"
          }
        }, 
        {
          "children": [
            "carta"
          ], 
          "name": "term", 
          "attrs": {
            "name": "letter"
          }
        }, 
        {
          "children": [
            "sin fecha"
          ], 
          "name": "term", 
          "attrs": {
            "name": "no date"
          }
        }, 
        {
          "children": [
            "s.\u00a0f."
          ], 
          "name": "term", 
          "attrs": {
            "name": "no date", 
            "form": "short"
          }
        }, 
        {
          "children": [
            "en l\u00ednea"
          ], 
          "name": "term", 
          "attrs": {
            "name": "online"
          }
        }, 
        {
          "children": [
            "presentado en"
          ], 
          "name": "term", 
          "attrs": {
            "name": "presented at"
          }
        }, 
        {
          "children": [
            {
              "children": [
                "referencia"
              ], 
              "name": "single", 
              "attrs": {}
            }, 
            {
              "children": [
                "referencias"
              ], 
              "name": "multiple", 
              "attrs": {}
            }
          ], 
          "name": "term", 
          "attrs": {
            "name": "reference"
          }
        }, 
        {
          "children": [
            {
              "children": [
                "ref."
              ], 
              "name": "single", 
              "attrs": {}
            }, 
            {
              "children": [
                "refs."
              ], 
              "name": "multiple", 
              "attrs": {}
            }
          ], 
          "name": "term", 
          "attrs": {
            "name": "reference", 
            "form": "short"
          }
        }, 
        {
          "children": [
            "recuperado"
          ], 
          "name": "term", 
          "attrs": {
            "name": "retrieved"
          }
        }, 
        {
          "children": [
            "escala"
          ], 
          "name": "term", 
          "attrs": {
            "name": "scale"
          }
        }, 
        {
          "children": [
            "versi\u00f3n"
          ], 
          "name": "term", 
          "attrs": {
            "name": "version"
          }
        }, 
        {
          "children": [
            "d.\u00a0C."
          ], 
          "name": "term", 
          "attrs": {
            "name": "ad"
          }
        }, 
        {
          "children": [
            "a.\u00a0C."
          ], 
          "name": "term", 
          "attrs": {
            "name": "bc"
          }
        }, 
        {
          "children": [
            "\u00ab"
          ], 
          "name": "term", 
          "attrs": {
            "name": "open-quote"
          }
        }, 
        {
          "children": [
            "\u00bb"
          ], 
          "name": "term", 
          "attrs": {
            "name": "close-quote"
          }
        }, 
        {
          "children": [
            "\u201c"
          ], 
          "name": "term", 
          "attrs": {
            "name": "open-inner-quote"
          }
        }, 
        {
          "children": [
            "\u201d"
          ], 
          "name": "term", 
          "attrs": {
            "name": "close-inner-quote"
          }
        }, 
        {
          "children": [
            "-"
          ], 
          "name": "term", 
          "attrs": {
            "name": "page-range-delimiter"
          }
        }, 
        {
          "children": [
            ".\u00aa"
          ], 
          "name": "term", 
          "attrs": {
            "name": "ordinal"
          }
        }, 
        {
          "children": [
            "primera"
          ], 
          "name": "term", 
          "attrs": {
            "name": "long-ordinal-01"
          }
        }, 
        {
          "children": [
            "segunda"
          ], 
          "name": "term", 
          "attrs": {
            "name": "long-ordinal-02"
          }
        }, 
        {
          "children": [
            "tercera"
          ], 
          "name": "term", 
          "attrs": {
            "name": "long-ordinal-03"
          }
        }, 
        {
          "children": [
            "cuarta"
          ], 
          "name": "term", 
          "attrs": {
            "name": "long-ordinal-04"
          }
        }, 
        {
          "children": [
            "quinta"
          ], 
          "name": "term", 
          "attrs": {
            "name": "long-ordinal-05"
          }
        }, 
        {
          "children": [
            "sexta"
          ], 
          "name": "term", 
          "attrs": {
            "name": "long-ordinal-06"
          }
        }, 
        {
          "children": [
            "s\u00e9ptima"
          ], 
          "name": "term", 
          "attrs": {
            "name": "long-ordinal-07"
          }
        }, 
        {
          "children": [
            "octava"
          ], 
          "name": "term", 
          "attrs": {
            "name": "long-ordinal-08"
          }
        }, 
        {
          "children": [
            "novena"
          ], 
          "name": "term", 
          "attrs": {
            "name": "long-ordinal-09"
          }
        }, 
        {
          "children": [
            "d\u00e9cima"
          ], 
          "name": "term", 
          "attrs": {
            "name": "long-ordinal-10"
          }
        }, 
        {
          "children": [
            {
              "children": [
                "libro"
              ], 
              "name": "single", 
              "attrs": {}
            }, 
            {
              "children": [
                "libros"
              ], 
              "name": "multiple", 
              "attrs": {}
            }
          ], 
          "name": "term", 
          "attrs": {
            "name": "book"
          }
        }, 
        {
          "children": [
            {
              "children": [
                "cap\u00edtulo"
              ], 
              "name": "single", 
              "attrs": {}
            }, 
            {
              "children": [
                "cap\u00edtulos"
              ], 
              "name": "multiple", 
              "attrs": {}
            }
          ], 
          "name": "term", 
          "attrs": {
            "name": "chapter"
          }
        }, 
        {
          "children": [
            {
              "children": [
                "columna"
              ], 
              "name": "single", 
              "attrs": {}
            }, 
            {
              "children": [
                "columnas"
              ], 
              "name": "multiple", 
              "attrs": {}
            }
          ], 
          "name": "term", 
          "attrs": {
            "name": "column"
          }
        }, 
        {
          "children": [
            {
              "children": [
                "figura"
              ], 
              "name": "single", 
              "attrs": {}
            }, 
            {
              "children": [
                "figuras"
              ], 
              "name": "multiple", 
              "attrs": {}
            }
          ], 
          "name": "term", 
          "attrs": {
            "name": "figure"
          }
        }, 
        {
          "children": [
            {
              "children": [
                "folio"
              ], 
              "name": "single", 
              "attrs": {}
            }, 
            {
              "children": [
                "folios"
              ], 
              "name": "multiple", 
              "attrs": {}
            }
          ], 
          "name": "term", 
          "attrs": {
            "name": "folio"
          }
        }, 
        {
          "children": [
            {
              "children": [
                "n\u00famero"
              ], 
              "name": "single", 
              "attrs": {}
            }, 
            {
              "children": [
                "n\u00fameros"
              ], 
              "name": "multiple", 
              "attrs": {}
            }
          ], 
          "name": "term", 
          "attrs": {
            "name": "issue"
          }
        }, 
        {
          "children": [
            {
              "children": [
                "l\u00ednea"
              ], 
              "name": "single", 
              "attrs": {}
            }, 
            {
              "children": [
                "l\u00edneas"
              ], 
              "name": "multiple", 
              "attrs": {}
            }
          ], 
          "name": "term", 
          "attrs": {
            "name": "line"
          }
        }, 
        {
          "children": [
            {
              "children": [
                "nota"
              ], 
              "name": "single", 
              "attrs": {}
            }, 
            {
              "children": [
                "notas"
              ], 
              "name": "multiple", 
              "attrs": {}
            }
          ], 
          "name": "term", 
          "attrs": {
            "name": "note"
          }
        }, 
        {
          "children": [
            {
              "children": [
                "opus"
              ], 
              "name": "single", 
              "attrs": {}
            }, 
            {
              "children": [
                "opera"
              ], 
              "name": "multiple", 
              "attrs": {}
            }
          ], 
          "name": "term", 
          "attrs": {
            "name": "opus"
          }
        }, 
        {
          "children": [
            {
              "children": [
                "p\u00e1gina"
              ], 
              "name": "single", 
              "attrs": {}
            }, 
            {
              "children": [
                "p\u00e1ginas"
              ], 
              "name": "multiple", 
              "attrs": {}
            }
          ], 
          "name": "term", 
          "attrs": {
            "name": "page"
          }
        }, 
        {
          "children": [
            {
              "children": [
                "p\u00e1gina"
              ], 
              "name": "single", 
              "attrs": {}
            }, 
            {
              "children": [
                "p\u00e1ginas"
              ], 
              "name": "multiple", 
              "attrs": {}
            }
          ], 
          "name": "term", 
          "attrs": {
            "name": "number-of-pages"
          }
        }, 
        {
          "children": [
            {
              "children": [
                "p\u00e1rrafo"
              ], 
              "name": "single", 
              "attrs": {}
            }, 
            {
              "children": [
                "p\u00e1rrafos"
              ], 
              "name": "multiple", 
              "attrs": {}
            }
          ], 
          "name": "term", 
          "attrs": {
            "name": "paragraph"
          }
        }, 
        {
          "children": [
            {
              "children": [
                "parte"
              ], 
              "name": "single", 
              "attrs": {}
            }, 
            {
              "children": [
                "partes"
              ], 
              "name": "multiple", 
              "attrs": {}
            }
          ], 
          "name": "term", 
          "attrs": {
            "name": "part"
          }
        }, 
        {
          "children": [
            {
              "children": [
                "secci\u00f3n"
              ], 
              "name": "single", 
              "attrs": {}
            }, 
            {
              "children": [
                "secciones"
              ], 
              "name": "multiple", 
              "attrs": {}
            }
          ], 
          "name": "term", 
          "attrs": {
            "name": "section"
          }
        }, 
        {
          "children": [
            {
              "children": [
                "sub voce"
              ], 
              "name": "single", 
              "attrs": {}
            }, 
            {
              "children": [
                "sub vocibus"
              ], 
              "name": "multiple", 
              "attrs": {}
            }
          ], 
          "name": "term", 
          "attrs": {
            "name": "sub verbo"
          }
        }, 
        {
          "children": [
            {
              "children": [
                "verso"
              ], 
              "name": "single", 
              "attrs": {}
            }, 
            {
              "children": [
                "versos"
              ], 
              "name": "multiple", 
              "attrs": {}
            }
          ], 
          "name": "term", 
          "attrs": {
            "name": "verse"
          }
        }, 
        {
          "children": [
            {
              "children": [
                "volumen"
              ], 
              "name": "single", 
              "attrs": {}
            }, 
            {
              "children": [
                "vol\u00famenes"
              ], 
              "name": "multiple", 
              "attrs": {}
            }
          ], 
          "name": "term", 
          "attrs": {
            "name": "volume"
          }
        }, 
        {
          "children": [
            "lib."
          ], 
          "name": "term", 
          "attrs": {
            "name": "book", 
            "form": "short"
          }
        }, 
        {
          "children": [
            "cap."
          ], 
          "name": "term", 
          "attrs": {
            "name": "chapter", 
            "form": "short"
          }
        }, 
        {
          "children": [
            "col."
          ], 
          "name": "term", 
          "attrs": {
            "name": "column", 
            "form": "short"
          }
        }, 
        {
          "children": [
            "fig."
          ], 
          "name": "term", 
          "attrs": {
            "name": "figure", 
            "form": "short"
          }
        }, 
        {
          "children": [
            "f."
          ], 
          "name": "term", 
          "attrs": {
            "name": "folio", 
            "form": "short"
          }
        }, 
        {
          "children": [
            "n.\u00ba"
          ], 
          "name": "term", 
          "attrs": {
            "name": "issue", 
            "form": "short"
          }
        }, 
        {
          "children": [
            "l."
          ], 
          "name": "term", 
          "attrs": {
            "name": "line", 
            "form": "short"
          }
        }, 
        {
          "children": [
            "n."
          ], 
          "name": "term", 
          "attrs": {
            "name": "note", 
            "form": "short"
          }
        }, 
        {
          "children": [
            "op."
          ], 
          "name": "term", 
          "attrs": {
            "name": "opus", 
            "form": "short"
          }
        }, 
        {
          "children": [
            {
              "children": [
                "p."
              ], 
              "name": "single", 
              "attrs": {}
            }, 
            {
              "children": [
                "pp."
              ], 
              "name": "multiple", 
              "attrs": {}
            }
          ], 
          "name": "term", 
          "attrs": {
            "name": "page", 
            "form": "short"
          }
        }, 
        {
          "children": [
            {
              "children": [
                "p."
              ], 
              "name": "single", 
              "attrs": {}
            }, 
            {
              "children": [
                "pp."
              ], 
              "name": "multiple", 
              "attrs": {}
            }
          ], 
          "name": "term", 
          "attrs": {
            "name": "number-of-pages", 
            "form": "short"
          }
        }, 
        {
          "children": [
            "p\u00e1rr."
          ], 
          "name": "term", 
          "attrs": {
            "name": "paragraph", 
            "form": "short"
          }
        }, 
        {
          "children": [
            "pt."
          ], 
          "name": "term", 
          "attrs": {
            "name": "part", 
            "form": "short"
          }
        }, 
        {
          "children": [
            "sec."
          ], 
          "name": "term", 
          "attrs": {
            "name": "section", 
            "form": "short"
          }
        }, 
        {
          "children": [
            {
              "children": [
                "s.\u00a0v."
              ], 
              "name": "single", 
              "attrs": {}
            }, 
            {
              "children": [
                "s.\u00a0vv."
              ], 
              "name": "multiple", 
              "attrs": {}
            }
          ], 
          "name": "term", 
          "attrs": {
            "name": "sub verbo", 
            "form": "short"
          }
        }, 
        {
          "children": [
            {
              "children": [
                "v."
              ], 
              "name": "single", 
              "attrs": {}
            }, 
            {
              "children": [
                "vv."
              ], 
              "name": "multiple", 
              "attrs": {}
            }
          ], 
          "name": "term", 
          "attrs": {
            "name": "verse", 
            "form": "short"
          }
        }, 
        {
          "children": [
            {
              "children": [
                "vol."
              ], 
              "name": "single", 
              "attrs": {}
            }, 
            {
              "children": [
                "vols."
              ], 
              "name": "multiple", 
              "attrs": {}
            }
          ], 
          "name": "term", 
          "attrs": {
            "name": "volume", 
            "form": "short"
          }
        }, 
        {
          "children": [
            {
              "children": [
                "\u00a7"
              ], 
              "name": "single", 
              "attrs": {}
            }, 
            {
              "children": [
                "\u00a7"
              ], 
              "name": "multiple", 
              "attrs": {}
            }
          ], 
          "name": "term", 
          "attrs": {
            "name": "paragraph", 
            "form": "symbol"
          }
        }, 
        {
          "children": [
            {
              "children": [
                "\u00a7"
              ], 
              "name": "single", 
              "attrs": {}
            }, 
            {
              "children": [
                "\u00a7"
              ], 
              "name": "multiple", 
              "attrs": {}
            }
          ], 
          "name": "term", 
          "attrs": {
            "name": "section", 
            "form": "symbol"
          }
        }, 
        {
          "children": [
            {
              "children": [
                "director"
              ], 
              "name": "single", 
              "attrs": {}
            }, 
            {
              "children": [
                "directores"
              ], 
              "name": "multiple", 
              "attrs": {}
            }
          ], 
          "name": "term", 
          "attrs": {
            "name": "director"
          }
        }, 
        {
          "children": [
            {
              "children": [
                "editor"
              ], 
              "name": "single", 
              "attrs": {}
            }, 
            {
              "children": [
                "editores"
              ], 
              "name": "multiple", 
              "attrs": {}
            }
          ], 
          "name": "term", 
          "attrs": {
            "name": "editor"
          }
        }, 
        {
          "children": [
            {
              "children": [
                "editor"
              ], 
              "name": "single", 
              "attrs": {}
            }, 
            {
              "children": [
                "editores"
              ], 
              "name": "multiple", 
              "attrs": {}
            }
          ], 
          "name": "term", 
          "attrs": {
            "name": "editorial-director"
          }
        }, 
        {
          "children": [
            {
              "children": [
                "ilustrador"
              ], 
              "name": "single", 
              "attrs": {}
            }, 
            {
              "children": [
                "ilustradores"
              ], 
              "name": "multiple", 
              "attrs": {}
            }
          ], 
          "name": "term", 
          "attrs": {
            "name": "illustrator"
          }
        }, 
        {
          "children": [
            {
              "children": [
                "traductor"
              ], 
              "name": "single", 
              "attrs": {}
            }, 
            {
              "children": [
                "traductores"
              ], 
              "name": "multiple", 
              "attrs": {}
            }
          ], 
          "name": "term", 
          "attrs": {
            "name": "translator"
          }
        }, 
        {
          "children": [
            {
              "children": [
                "editor y traductor"
              ], 
              "name": "single", 
              "attrs": {}
            }, 
            {
              "children": [
                "editores y traductores"
              ], 
              "name": "multiple", 
              "attrs": {}
            }
          ], 
          "name": "term", 
          "attrs": {
            "name": "editortranslator"
          }
        }, 
        {
          "children": [
            {
              "children": [
                "dir."
              ], 
              "name": "single", 
              "attrs": {}
            }, 
            {
              "children": [
                "dirs."
              ], 
              "name": "multiple", 
              "attrs": {}
            }
          ], 
          "name": "term", 
          "attrs": {
            "name": "director", 
            "form": "short"
          }
        }, 
        {
          "children": [
            {
              "children": [
                "ed."
              ], 
              "name": "single", 
              "attrs": {}
            }, 
            {
              "children": [
                "eds."
              ], 
              "name": "multiple", 
              "attrs": {}
            }
          ], 
          "name": "term", 
          "attrs": {
            "name": "editor", 
            "form": "short"
          }
        }, 
        {
          "children": [
            {
              "children": [
                "ed."
              ], 
              "name": "single", 
              "attrs": {}
            }, 
            {
              "children": [
                "eds."
              ], 
              "name": "multiple", 
              "attrs": {}
            }
          ], 
          "name": "term", 
          "attrs": {
            "name": "editorial-director", 
            "form": "short"
          }
        }, 
        {
          "children": [
            {
              "children": [
                "ilust."
              ], 
              "name": "single", 
              "attrs": {}
            }, 
            {
              "children": [
                "ilusts."
              ], 
              "name": "multiple", 
              "attrs": {}
            }
          ], 
          "name": "term", 
          "attrs": {
            "name": "illustrator", 
            "form": "short"
          }
        }, 
        {
          "children": [
            {
              "children": [
                "trad."
              ], 
              "name": "single", 
              "attrs": {}
            }, 
            {
              "children": [
                "trads."
              ], 
              "name": "multiple", 
              "attrs": {}
            }
          ], 
          "name": "term", 
          "attrs": {
            "name": "translator", 
            "form": "short"
          }
        }, 
        {
          "children": [
            {
              "children": [
                "ed. y trad."
              ], 
              "name": "single", 
              "attrs": {}
            }, 
            {
              "children": [
                "eds. y trads."
              ], 
              "name": "multiple", 
              "attrs": {}
            }
          ], 
          "name": "term", 
          "attrs": {
            "name": "editortranslator", 
            "form": "short"
          }
        }, 
        {
          "children": [
            "de"
          ], 
          "name": "term", 
          "attrs": {
            "name": "container-author", 
            "form": "verb"
          }
        }, 
        {
          "children": [
            "dirigido por"
          ], 
          "name": "term", 
          "attrs": {
            "name": "director", 
            "form": "verb"
          }
        }, 
        {
          "children": [
            "editado por"
          ], 
          "name": "term", 
          "attrs": {
            "name": "editor", 
            "form": "verb"
          }
        }, 
        {
          "children": [
            "editado por"
          ], 
          "name": "term", 
          "attrs": {
            "name": "editorial-director", 
            "form": "verb"
          }
        }, 
        {
          "children": [
            "ilustrado por"
          ], 
          "name": "term", 
          "attrs": {
            "name": "illustrator", 
            "form": "verb"
          }
        }, 
        {
          "children": [
            "entrevistado por"
          ], 
          "name": "term", 
          "attrs": {
            "name": "interviewer", 
            "form": "verb"
          }
        }, 
        {
          "children": [
            "a"
          ], 
          "name": "term", 
          "attrs": {
            "name": "recipient", 
            "form": "verb"
          }
        }, 
        {
          "children": [
            "por"
          ], 
          "name": "term", 
          "attrs": {
            "name": "reviewed-author", 
            "form": "verb"
          }
        }, 
        {
          "children": [
            "traducido por"
          ], 
          "name": "term", 
          "attrs": {
            "name": "translator", 
            "form": "verb"
          }
        }, 
        {
          "children": [
            "editado y traducido por"
          ], 
          "name": "term", 
          "attrs": {
            "name": "editortranslator", 
            "form": "verb"
          }
        }, 
        {
          "children": [
            "dir."
          ], 
          "name": "term", 
          "attrs": {
            "name": "director", 
            "form": "verb-short"
          }
        }, 
        {
          "children": [
            "ed."
          ], 
          "name": "term", 
          "attrs": {
            "name": "editor", 
            "form": "verb-short"
          }
        }, 
        {
          "children": [
            "ed."
          ], 
          "name": "term", 
          "attrs": {
            "name": "editorial-director", 
            "form": "verb-short"
          }
        }, 
        {
          "children": [
            "ilust."
          ], 
          "name": "term", 
          "attrs": {
            "name": "illustrator", 
            "form": "verb-short"
          }
        }, 
        {
          "children": [
            "trad."
          ], 
          "name": "term", 
          "attrs": {
            "name": "translator", 
            "form": "verb-short"
          }
        }, 
        {
          "children": [
            "ed. y trad."
          ], 
          "name": "term", 
          "attrs": {
            "name": "editortranslator", 
            "form": "verb-short"
          }
        }, 
        {
          "children": [
            "enero"
          ], 
          "name": "term", 
          "attrs": {
            "name": "month-01"
          }
        }, 
        {
          "children": [
            "febrero"
          ], 
          "name": "term", 
          "attrs": {
            "name": "month-02"
          }
        }, 
        {
          "children": [
            "marzo"
          ], 
          "name": "term", 
          "attrs": {
            "name": "month-03"
          }
        }, 
        {
          "children": [
            "abril"
          ], 
          "name": "term", 
          "attrs": {
            "name": "month-04"
          }
        }, 
        {
          "children": [
            "mayo"
          ], 
          "name": "term", 
          "attrs": {
            "name": "month-05"
          }
        }, 
        {
          "children": [
            "junio"
          ], 
          "name": "term", 
          "attrs": {
            "name": "month-06"
          }
        }, 
        {
          "children": [
            "julio"
          ], 
          "name": "term", 
          "attrs": {
            "name": "month-07"
          }
        }, 
        {
          "children": [
            "agosto"
          ], 
          "name": "term", 
          "attrs": {
            "name": "month-08"
          }
        }, 
        {
          "children": [
            "septiembre"
          ], 
          "name": "term", 
          "attrs": {
            "name": "month-09"
          }
        }, 
        {
          "children": [
            "octubre"
          ], 
          "name": "term", 
          "attrs": {
            "name": "month-10"
          }
        }, 
        {
          "children": [
            "noviembre"
          ], 
          "name": "term", 
          "attrs": {
            "name": "month-11"
          }
        }, 
        {
          "children": [
            "diciembre"
          ], 
          "name": "term", 
          "attrs": {
            "name": "month-12"
          }
        }, 
        {
          "children": [
            "ene."
          ], 
          "name": "term", 
          "attrs": {
            "name": "month-01", 
            "form": "short"
          }
        }, 
        {
          "children": [
            "feb."
          ], 
          "name": "term", 
          "attrs": {
            "name": "month-02", 
            "form": "short"
          }
        }, 
        {
          "children": [
            "mar."
          ], 
          "name": "term", 
          "attrs": {
            "name": "month-03", 
            "form": "short"
          }
        }, 
        {
          "children": [
            "abr."
          ], 
          "name": "term", 
          "attrs": {
            "name": "month-04", 
            "form": "short"
          }
        }, 
        {
          "children": [
            "may"
          ], 
          "name": "term", 
          "attrs": {
            "name": "month-05", 
            "form": "short"
          }
        }, 
        {
          "children": [
            "jun."
          ], 
          "name": "term", 
          "attrs": {
            "name": "month-06", 
            "form": "short"
          }
        }, 
        {
          "children": [
            "jul."
          ], 
          "name": "term", 
          "attrs": {
            "name": "month-07", 
            "form": "short"
          }
        }, 
        {
          "children": [
            "ago."
          ], 
          "name": "term", 
          "attrs": {
            "name": "month-08", 
            "form": "short"
          }
        }, 
        {
          "children": [
            "sep."
          ], 
          "name": "term", 
          "attrs": {
            "name": "month-09", 
            "form": "short"
          }
        }, 
        {
          "children": [
            "oct."
          ], 
          "name": "term", 
          "attrs": {
            "name": "month-10", 
            "form": "short"
          }
        }, 
        {
          "children": [
            "nov."
          ], 
          "name": "term", 
          "attrs": {
            "name": "month-11", 
            "form": "short"
          }
        }, 
        {
          "children": [
            "dic."
          ], 
          "name": "term", 
          "attrs": {
            "name": "month-12", 
            "form": "short"
          }
        }, 
        {
          "children": [
            "primavera"
          ], 
          "name": "term", 
          "attrs": {
            "name": "season-01"
          }
        }, 
        {
          "children": [
            "verano"
          ], 
          "name": "term", 
          "attrs": {
            "name": "season-02"
          }
        }, 
        {
          "children": [
            "oto\u00f1o"
          ], 
          "name": "term", 
          "attrs": {
            "name": "season-03"
          }
        }, 
        {
          "children": [
            "invierno"
          ], 
          "name": "term", 
          "attrs": {
            "name": "season-04"
          }
        }
      ], 
      "name": "terms", 
      "attrs": {}
    }
  ], 
  "name": "locale", 
  "attrs": {
    "xmlns": "http://purl.org/net/xbiblio/csl", 
    "version": "1.0", 
    "xml:lang": "es-ES"
  }
}