{
  "children": [
    {
      "children": [
        {
          "children": [
            {
              "children": [], 
              "name": "name", 
              "attrs": {}
            }
          ], 
          "name": "translator", 
          "attrs": {}
        }, 
        {
          "children": [
            {
              "children": [], 
              "name": "name", 
              "attrs": {}
            }
          ], 
          "name": "translator", 
          "attrs": {}
        }, 
        {
          "children": [
            {
              "children": [], 
              "name": "name", 
              "attrs": {}
            }
          ], 
          "name": "translator", 
          "attrs": {}
        }, 
        {
          "children": [
            {
              "children": [], 
              "name": "name", 
              "attrs": {}
            }
          ], 
          "name": "translator", 
          "attrs": {}
        }, 
        {
          "children": [], 
          "name": "rights", 
          "attrs": {
            "license": "http://creativecommons.org/licenses/by-sa/3.0/"
          }
        }, 
        {
          "children": [], 
          "name": "updated", 
          "attrs": {}
        }
      ], 
      "name": "info", 
      "attrs": {}
    }, 
    {
      "children": [], 
      "name": "style-options", 
      "attrs": {
        "punctuation-in-quote": "false"
      }
    }, 
    {
      "children": [
        {
          "children": [], 
          "name": "date-part", 
          "attrs": {
            "name": "day", 
            "form": "ordinal", 
            "suffix": " "
          }
        }, 
        {
          "children": [], 
          "name": "date-part", 
          "attrs": {
            "name": "month", 
            "suffix": " "
          }
        }, 
        {
          "children": [], 
          "name": "date-part", 
          "attrs": {
            "name": "year"
          }
        }
      ], 
      "name": "date", 
      "attrs": {
        "form": "text"
      }
    }, 
    {
      "children": [
        {
          "children": [], 
          "name": "date-part", 
          "attrs": {
            "name": "day", 
            "suffix": "."
          }
        }, 
        {
          "children": [], 
          "name": "date-part", 
          "attrs": {
            "name": "month", 
            "form": "numeric", 
            "suffix": "."
          }
        }, 
        {
          "children": [], 
          "name": "date-part", 
          "attrs": {
            "name": "year"
          }
        }
      ], 
      "name": "date", 
      "attrs": {
        "form": "numeric"
      }
    }, 
    {
      "children": [
        {
          "children": [
            "viitattu"
          ], 
          "name": "term", 
          "attrs": {
            "name": "accessed"
          }
        }, 
        {
          "children": [
            "ja"
          ], 
          "name": "term", 
          "attrs": {
            "name": "and"
          }
        }, 
        {
          "children": [
            "ym."
          ], 
          "name": "term", 
          "attrs": {
            "name": "and others"
          }
        }, 
        {
          "children": [
            "tuntematon"
          ], 
          "name": "term", 
          "attrs": {
            "name": "anonymous"
          }
        }, 
        {
          "children": [
            "tuntematon"
          ], 
          "name": "term", 
          "attrs": {
            "name": "anonymous", 
            "form": "short"
          }
        }, 
        {
          "children": [
            "osoitteessa"
          ], 
          "name": "term", 
          "attrs": {
            "name": "at"
          }
        }, 
        {
          "children": [
            "saatavissa"
          ], 
          "name": "term", 
          "attrs": {
            "name": "available at"
          }
        }, 
        {
          "children": [
            "tekij\u00e4"
          ], 
          "name": "term", 
          "attrs": {
            "name": "by"
          }
        }, 
        {
          "children": [
            "noin"
          ], 
          "name": "term", 
          "attrs": {
            "name": "circa"
          }
        }, 
        {
          "children": [
            "n."
          ], 
          "name": "term", 
          "attrs": {
            "name": "circa", 
            "form": "short"
          }
        }, 
        {
          "children": [
            "viitattu"
          ], 
          "name": "term", 
          "attrs": {
            "name": "cited"
          }
        }, 
        {
          "children": [
            {
              "children": [
                "painos"
              ], 
              "name": "single", 
              "attrs": {}
            }, 
            {
              "children": [
                "painokset"
              ], 
              "name": "multiple", 
              "attrs": {}
            }
          ], 
          "name": "term", 
          "attrs": {
            "name": "edition"
          }
        }, 
        {
          "children": [
            "p."
          ], 
          "name": "term", 
          "attrs": {
            "name": "edition", 
            "form": "short"
          }
        }, 
        {
          "children": [
            "ym."
          ], 
          "name": "term", 
          "attrs": {
            "name": "et-al"
          }
        }, 
        {
          "children": [
            "tulossa"
          ], 
          "name": "term", 
          "attrs": {
            "name": "forthcoming"
          }
        }, 
        {
          "children": [
            "osoitteesta"
          ], 
          "name": "term", 
          "attrs": {
            "name": "from"
          }
        }, 
        {
          "children": [
            "mt."
          ], 
          "name": "term", 
          "attrs": {
            "name": "ibid"
          }
        }, 
        {
          "children": [
            "teoksessa"
          ], 
          "name": "term", 
          "attrs": {
            "name": "in"
          }
        }, 
        {
          "children": [
            "painossa"
          ], 
          "name": "term", 
          "attrs": {
            "name": "in press"
          }
        }, 
        {
          "children": [
            "internet"
          ], 
          "name": "term", 
          "attrs": {
            "name": "internet"
          }
        }, 
        {
          "children": [
            "haastattelu"
          ], 
          "name": "term", 
          "attrs": {
            "name": "interview"
          }
        }, 
        {
          "children": [
            "kirje"
          ], 
          "name": "term", 
          "attrs": {
            "name": "letter"
          }
        }, 
        {
          "children": [
            "ei p\u00e4iv\u00e4m\u00e4\u00e4r\u00e4\u00e4"
          ], 
          "name": "term", 
          "attrs": {
            "name": "no date"
          }
        }, 
        {
          "children": [
            "ei pvm."
          ], 
          "name": "term", 
          "attrs": {
            "name": "no date", 
            "form": "short"
          }
        }, 
        {
          "children": [
            "verkossa"
          ], 
          "name": "term", 
          "attrs": {
            "name": "online"
          }
        }, 
        {
          "children": [
            "esitetty tilaisuudessa"
          ], 
          "name": "term", 
          "attrs": {
            "name": "presented at"
          }
        }, 
        {
          "children": [
            {
              "children": [
                "viittaus"
              ], 
              "name": "single", 
              "attrs": {}
            }, 
            {
              "children": [
                "viittaukset"
              ], 
              "name": "multiple", 
              "attrs": {}
            }
          ], 
          "name": "term", 
          "attrs": {
            "name": "reference"
          }
        }, 
        {
          "children": [
            {
              "children": [
                "viit."
              ], 
              "name": "single", 
              "attrs": {}
            }, 
            {
              "children": [
                "viit."
              ], 
              "name": "multiple", 
              "attrs": {}
            }
          ], 
          "name": "term", 
          "attrs": {
            "name": "reference", 
            "form": "short"
          }
        }, 
        {
          "children": [
            "noudettu"
          ], 
          "name": "term", 
          "attrs": {
            "name": "retrieved"
          }
        }, 
        {
          "children": [
            "mittakaava"
          ], 
          "name": "term", 
          "attrs": {
            "name": "scale"
          }
        }, 
        {
          "children": [
            "versio"
          ], 
          "name": "term", 
          "attrs": {
            "name": "version"
          }
        }, 
        {
          "children": [
            "jaa."
          ], 
          "name": "term", 
          "attrs": {
            "name": "ad"
          }
        }, 
        {
          "children": [
            "eaa."
          ], 
          "name": "term", 
          "attrs": {
            "name": "bc"
          }
        }, 
        {
          "children": [
            "\u201d"
          ], 
          "name": "term", 
          "attrs": {
            "name": "open-quote"
          }
        }, 
        {
          "children": [
            "\u201d"
          ], 
          "name": "term", 
          "attrs": {
            "name": "close-quote"
          }
        }, 
        {
          "children": [
            "\u2019"
          ], 
          "name": "term", 
          "attrs": {
            "name": "open-inner-quote"
          }
        }, 
        {
          "children": [
            "\u2019"
          ], 
          "name": "term", 
          "attrs": {
            "name": "close-inner-quote"
          }
        }, 
        {
          "children": [
            "\u2013"
          ], 
          "name": "term", 
          "attrs": {
            "name": "page-range-delimiter"
          }
        }, 
        {
          "children": [
            "."
          ], 
          "name": "term", 
          "attrs": {
            "name": "ordinal"
          }
        }, 
        {
          "children": [
            "ensimm\u00e4inen"
          ], 
          "name": "term", 
          "attrs": {
            "name": "long-ordinal-01"
          }
        }, 
        {
          "children": [
            "toinen"
          ], 
          "name": "term", 
          "attrs": {
            "name": "long-ordinal-02"
          }
        }, 
        {
          "children": [
            "kolmas"
          ], 
          "name": "term", 
          "attrs": {
            "name": "long-ordinal-03"
          }
        }, 
        {
          "children": [
            "nelj\u00e4s"
          ], 
          "name": "term", 
          "attrs": {
            "name": "long-ordinal-04"
          }
        }, 
        {
          "children": [
            "viides"
          ], 
          "name": "term", 
          "attrs": {
            "name": "long-ordinal-05"
          }
        }, 
        {
          "children": [
            "kuudes"
          ], 
          "name": "term", 
          "attrs": {
            "name": "long-ordinal-06"
          }
        }, 
        {
          "children": [
            "seitsem\u00e4s"
          ], 
          "name": "term", 
          "attrs": {
            "name": "long-ordinal-07"
          }
        }, 
        {
          "children": [
            "kahdeksas"
          ], 
          "name": "term", 
          "attrs": {
            "name": "long-ordinal-08"
          }
        }, 
        {
          "children": [
            "yhdeks\u00e4s"
          ], 
          "name": "term", 
          "attrs": {
            "name": "long-ordinal-09"
          }
        }, 
        {
          "children": [
            "kymmenes"
          ], 
          "name": "term", 
          "attrs": {
            "name": "long-ordinal-10"
          }
        }, 
        {
          "children": [
            {
              "children": [
                "kirja"
              ], 
              "name": "single", 
              "attrs": {}
            }, 
            {
              "children": [
                "kirjat"
              ], 
              "name": "multiple", 
              "attrs": {}
            }
          ], 
          "name": "term", 
          "attrs": {
            "name": "book"
          }
        }, 
        {
          "children": [
            {
              "children": [
                "luku"
              ], 
              "name": "single", 
              "attrs": {}
            }, 
            {
              "children": [
                "luvut"
              ], 
              "name": "multiple", 
              "attrs": {}
            }
          ], 
          "name": "term", 
          "attrs": {
            "name": "chapter"
          }
        }, 
        {
          "children": [
            {
              "children": [
                "palsta"
              ], 
              "name": "single", 
              "attrs": {}
            }, 
            {
              "children": [
                "palstat"
              ], 
              "name": "multiple", 
              "attrs": {}
            }
          ], 
          "name": "term", 
          "attrs": {
            "name": "column"
          }
        }, 
        {
          "children": [
            {
              "children": [
                "kuvio"
              ], 
              "name": "single", 
              "attrs": {}
            }, 
            {
              "children": [
                "kuviot"
              ], 
              "name": "multiple", 
              "attrs": {}
            }
          ], 
          "name": "term", 
          "attrs": {
            "name": "figure"
          }
        }, 
        {
          "children": [
            {
              "children": [
                "folio"
              ], 
              "name": "single", 
              "attrs": {}
            }, 
            {
              "children": [
                "foliot"
              ], 
              "name": "multiple", 
              "attrs": {}
            }
          ], 
          "name": "term", 
          "attrs": {
            "name": "folio"
          }
        }, 
        {
          "children": [
            {
              "children": [
                "numero"
              ], 
              "name": "single", 
              "attrs": {}
            }, 
            {
              "children": [
                "numerot"
              ], 
              "name": "multiple", 
              "attrs": {}
            }
          ], 
          "name": "term", 
          "attrs": {
            "name": "issue"
          }
        }, 
        {
          "children": [
            {
              "children": [
                "rivi"
              ], 
              "name": "single", 
              "attrs": {}
            }, 
            {
              "children": [
                "rivit"
              ], 
              "name": "multiple", 
              "attrs": {}
            }
          ], 
          "name": "term", 
          "attrs": {
            "name": "line"
          }
        }, 
        {
          "children": [
            {
              "children": [
                "huomautus"
              ], 
              "name": "single", 
              "attrs": {}
            }, 
            {
              "children": [
                "huomautukset"
              ], 
              "name": "multiple", 
              "attrs": {}
            }
          ], 
          "name": "term", 
          "attrs": {
            "name": "note"
          }
        }, 
        {
          "children": [
            {
              "children": [
                "opus"
              ], 
              "name": "single", 
              "attrs": {}
            }, 
            {
              "children": [
                "opukset"
              ], 
              "name": "multiple", 
              "attrs": {}
            }
          ], 
          "name": "term", 
          "attrs": {
            "name": "opus"
          }
        }, 
        {
          "children": [
            {
              "children": [
                "sivu"
              ], 
              "name": "single", 
              "attrs": {}
            }, 
            {
              "children": [
                "sivut"
              ], 
              "name": "multiple", 
              "attrs": {}
            }
          ], 
          "name": "term", 
          "attrs": {
            "name": "page"
          }
        }, 
        {
          "children": [
            {
              "children": [
                "sivu"
              ], 
              "name": "single", 
              "attrs": {}
            }, 
            {
              "children": [
                "sivut"
              ], 
              "name": "multiple", 
              "attrs": {}
            }
          ], 
          "name": "term", 
          "attrs": {
            "name": "number-of-pages"
          }
        }, 
        {
          "children": [
            {
              "children": [
                "kappale"
              ], 
              "name": "single", 
              "attrs": {}
            }, 
            {
              "children": [
                "kappaleet"
              ], 
              "name": "multiple", 
              "attrs": {}
            }
          ], 
          "name": "term", 
          "attrs": {
            "name": "paragraph"
          }
        }, 
        {
          "children": [
            {
              "children": [
                "osa"
              ], 
              "name": "single", 
              "attrs": {}
            }, 
            {
              "children": [
                "osat"
              ], 
              "name": "multiple", 
              "attrs": {}
            }
          ], 
          "name": "term", 
          "attrs": {
            "name": "part"
          }
        }, 
        {
          "children": [
            {
              "children": [
                "osa"
              ], 
              "name": "single", 
              "attrs": {}
            }, 
            {
              "children": [
                "osat"
              ], 
              "name": "multiple", 
              "attrs": {}
            }
          ], 
          "name": "term", 
          "attrs": {
            "name": "section"
          }
        }, 
        {
          "children": [
            {
              "children": [
                "sub verbo"
              ], 
              "name": "single", 
              "attrs": {}
            }, 
            {
              "children": [
                "sub verbis"
              ], 
              "name": "multiple", 
              "attrs": {}
            }
          ], 
          "name": "term", 
          "attrs": {
            "name": "sub verbo"
          }
        }, 
        {
          "children": [
            {
              "children": [
                "s\u00e4keist\u00f6"
              ], 
              "name": "single", 
              "attrs": {}
            }, 
            {
              "children": [
                "s\u00e4keist\u00f6t"
              ], 
              "name": "multiple", 
              "attrs": {}
            }
          ], 
          "name": "term", 
          "attrs": {
            "name": "verse"
          }
        }, 
        {
          "children": [
            {
              "children": [
                "vuosikerta"
              ], 
              "name": "single", 
              "attrs": {}
            }, 
            {
              "children": [
                "vuosikerrat"
              ], 
              "name": "multiple", 
              "attrs": {}
            }
          ], 
          "name": "term", 
          "attrs": {
            "name": "volume"
          }
        }, 
        {
          "children": [
            "kirja"
          ], 
          "name": "term", 
          "attrs": {
            "name": "book", 
            "form": "short"
          }
        }, 
        {
          "children": [
            "luku"
          ], 
          "name": "term", 
          "attrs": {
            "name": "chapter", 
            "form": "short"
          }
        }, 
        {
          "children": [
            "palsta"
          ], 
          "name": "term", 
          "attrs": {
            "name": "column", 
            "form": "short"
          }
        }, 
        {
          "children": [
            "kuv."
          ], 
          "name": "term", 
          "attrs": {
            "name": "figure", 
            "form": "short"
          }
        }, 
        {
          "children": [
            "fol."
          ], 
          "name": "term", 
          "attrs": {
            "name": "folio", 
            "form": "short"
          }
        }, 
        {
          "children": [
            "nro"
          ], 
          "name": "term", 
          "attrs": {
            "name": "issue", 
            "form": "short"
          }
        }, 
        {
          "children": [
            "r."
          ], 
          "name": "term", 
          "attrs": {
            "name": "line", 
            "form": "short"
          }
        }, 
        {
          "children": [
            "huom."
          ], 
          "name": "term", 
          "attrs": {
            "name": "note", 
            "form": "short"
          }
        }, 
        {
          "children": [
            "op."
          ], 
          "name": "term", 
          "attrs": {
            "name": "opus", 
            "form": "short"
          }
        }, 
        {
          "children": [
            {
              "children": [
                "s."
              ], 
              "name": "single", 
              "attrs": {}
            }, 
            {
              "children": [
                "ss."
              ], 
              "name": "multiple", 
              "attrs": {}
            }
          ], 
          "name": "term", 
          "attrs": {
            "name": "page", 
            "form": "short"
          }
        }, 
        {
          "children": [
            {
              "children": [
                "s."
              ], 
              "name": "single", 
              "attrs": {}
            }, 
            {
              "children": [
                "ss."
              ], 
              "name": "multiple", 
              "attrs": {}
            }
          ], 
          "name": "term", 
          "attrs": {
            "name": "number-of-pages", 
            "form": "short"
          }
        }, 
        {
          "children": [
            "kappale"
          ], 
          "name": "term", 
          "attrs": {
            "name": "paragraph", 
            "form": "short"
          }
        }, 
        {
          "children": [
            "osa"
          ], 
          "name": "term", 
          "attrs": {
            "name": "part", 
            "form": "short"
          }
        }, 
        {
          "children": [
            "osa"
          ], 
          "name": "term", 
          "attrs": {
            "name": "section", 
            "form": "short"
          }
        }, 
        {
          "children": [
            {
              "children": [
                "s.v."
              ], 
              "name": "single", 
              "attrs": {}
            }, 
            {
              "children": [
                "s.vv."
              ], 
              "name": "multiple", 
              "attrs": {}
            }
          ], 
          "name": "term", 
          "attrs": {
            "name": "sub verbo", 
            "form": "short"
          }
        }, 
        {
          "children": [
            {
              "children": [
                "s\u00e4k."
              ], 
              "name": "single", 
              "attrs": {}
            }, 
            {
              "children": [
                "s\u00e4k."
              ], 
              "name": "multiple", 
              "attrs": {}
            }
          ], 
          "name": "term", 
          "attrs": {
            "name": "verse", 
            "form": "short"
          }
        }, 
        {
          "children": [
            {
              "children": [
                "vsk."
              ], 
              "name": "single", 
              "attrs": {}
            }, 
            {
              "children": [
                "vsk."
              ], 
              "name": "multiple", 
              "attrs": {}
            }
          ], 
          "name": "term", 
          "attrs": {
            "name": "volume", 
            "form": "short"
          }
        }, 
        {
          "children": [
            {
              "children": [
                "\u00b6"
              ], 
              "name": "single", 
              "attrs": {}
            }, 
            {
              "children": [
                "\u00b6\u00b6"
              ], 
              "name": "multiple", 
              "attrs": {}
            }
          ], 
          "name": "term", 
          "attrs": {
            "name": "paragraph", 
            "form": "symbol"
          }
        }, 
        {
          "children": [
            {
              "children": [
                "\u00a7"
              ], 
              "name": "single", 
              "attrs": {}
            }, 
            {
              "children": [
                "\u00a7\u00a7"
              ], 
              "name": "multiple", 
              "attrs": {}
            }
          ], 
          "name": "term", 
          "attrs": {
            "name": "section", 
            "form": "symbol"
          }
        }, 
        {
          "children": [
            {
              "children": [
                "ohjaaja"
              ], 
              "name": "single", 
              "attrs": {}
            }, 
            {
              "children": [
                "ohjaajat"
              ], 
              "name": "multiple", 
              "attrs": {}
            }
          ], 
          "name": "term", 
          "attrs": {
            "name": "director"
          }
        }, 
        {
          "children": [
            {
              "children": [
                "toimittaja"
              ], 
              "name": "single", 
              "attrs": {}
            }, 
            {
              "children": [
                "toimittajat"
              ], 
              "name": "multiple", 
              "attrs": {}
            }
          ], 
          "name": "term", 
          "attrs": {
            "name": "editor"
          }
        }, 
        {
          "children": [
            {
              "children": [
                "toimittaja"
              ], 
              "name": "single", 
              "attrs": {}
            }, 
            {
              "children": [
                "toimittajat"
              ], 
              "name": "multiple", 
              "attrs": {}
            }
          ], 
          "name": "term", 
          "attrs": {
            "name": "editorial-director"
          }
        }, 
        {
          "children": [
            {
              "children": [
                "kuvittaja"
              ], 
              "name": "single", 
              "attrs": {}
            }, 
            {
              "children": [
                "kuvittajat"
              ], 
              "name": "multiple", 
              "attrs": {}
            }
          ], 
          "name": "term", 
          "attrs": {
            "name": "illustrator"
          }
        }, 
        {
          "children": [
            {
              "children": [
                "k\u00e4\u00e4nt\u00e4j\u00e4"
              ], 
              "name": "single", 
              "attrs": {}
            }, 
            {
              "children": [
                "k\u00e4\u00e4nt\u00e4j\u00e4t"
              ], 
              "name": "multiple", 
              "attrs": {}
            }
          ], 
          "name": "term", 
          "attrs": {
            "name": "translator"
          }
        }, 
        {
          "children": [
            {
              "children": [
                "toimittaja ja k\u00e4\u00e4nt\u00e4j\u00e4"
              ], 
              "name": "single", 
              "attrs": {}
            }, 
            {
              "children": [
                "toimittajat ja k\u00e4\u00e4nt\u00e4j\u00e4t"
              ], 
              "name": "multiple", 
              "attrs": {}
            }
          ], 
          "name": "term", 
          "attrs": {
            "name": "editortranslator"
          }
        }, 
        {
          "children": [
            {
              "children": [
                "ohj."
              ], 
              "name": "single", 
              "attrs": {}
            }, 
            {
              "children": [
                "ohj."
              ], 
              "name": "multiple", 
              "attrs": {}
            }
          ], 
          "name": "term", 
          "attrs": {
            "name": "director", 
            "form": "short"
          }
        }, 
        {
          "children": [
            {
              "children": [
                "toim."
              ], 
              "name": "single", 
              "attrs": {}
            }, 
            {
              "children": [
                "toim."
              ], 
              "name": "multiple", 
              "attrs": {}
            }
          ], 
          "name": "term", 
          "attrs": {
            "name": "editor", 
            "form": "short"
          }
        }, 
        {
          "children": [
            {
              "children": [
                "toim."
              ], 
              "name": "single", 
              "attrs": {}
            }, 
            {
              "children": [
                "toim."
              ], 
              "name": "multiple", 
              "attrs": {}
            }
          ], 
          "name": "term", 
          "attrs": {
            "name": "editorial-director", 
            "form": "short"
          }
        }, 
        {
          "children": [
            {
              "children": [
                "kuv."
              ], 
              "name": "single", 
              "attrs": {}
            }, 
            {
              "children": [
                "kuv."
              ], 
              "name": "multiple", 
              "attrs": {}
            }
          ], 
          "name": "term", 
          "attrs": {
            "name": "illustrator", 
            "form": "short"
          }
        }, 
        {
          "children": [
            {
              "children": [
                "k\u00e4\u00e4nt."
              ], 
              "name": "single", 
              "attrs": {}
            }, 
            {
              "children": [
                "k\u00e4\u00e4nt."
              ], 
              "name": "multiple", 
              "attrs": {}
            }
          ], 
          "name": "term", 
          "attrs": {
            "name": "translator", 
            "form": "short"
          }
        }, 
        {
          "children": [
            {
              "children": [
                "toim. ja k\u00e4\u00e4nt."
              ], 
              "name": "single", 
              "attrs": {}
            }, 
            {
              "children": [
                "toim. ja k\u00e4\u00e4nt."
              ], 
              "name": "multiple", 
              "attrs": {}
            }
          ], 
          "name": "term", 
          "attrs": {
            "name": "editortranslator", 
            "form": "short"
          }
        }, 
        {
          "children": [
            ""
          ], 
          "name": "term", 
          "attrs": {
            "name": "container-author", 
            "form": "verb"
          }
        }, 
        {
          "children": [
            "ohjannut"
          ], 
          "name": "term", 
          "attrs": {
            "name": "director", 
            "form": "verb"
          }
        }, 
        {
          "children": [
            "toimittanut"
          ], 
          "name": "term", 
          "attrs": {
            "name": "editor", 
            "form": "verb"
          }
        }, 
        {
          "children": [
            "toimittanut"
          ], 
          "name": "term", 
          "attrs": {
            "name": "editorial-director", 
            "form": "verb"
          }
        }, 
        {
          "children": [
            "kuvittanut"
          ], 
          "name": "term", 
          "attrs": {
            "name": "illustrator", 
            "form": "verb"
          }
        }, 
        {
          "children": [
            "haastatellut"
          ], 
          "name": "term", 
          "attrs": {
            "name": "interviewer", 
            "form": "verb"
          }
        }, 
        {
          "children": [
            "vastaanottaja"
          ], 
          "name": "term", 
          "attrs": {
            "name": "recipient", 
            "form": "verb"
          }
        }, 
        {
          "children": [
            ""
          ], 
          "name": "term", 
          "attrs": {
            "name": "reviewed-author", 
            "form": "verb"
          }
        }, 
        {
          "children": [
            "k\u00e4\u00e4nt\u00e4nyt"
          ], 
          "name": "term", 
          "attrs": {
            "name": "translator", 
            "form": "verb"
          }
        }, 
        {
          "children": [
            "toimittanut ja k\u00e4\u00e4nt\u00e4nyt"
          ], 
          "name": "term", 
          "attrs": {
            "name": "editortranslator", 
            "form": "verb"
          }
        }, 
        {
          "children": [
            "ohj."
          ], 
          "name": "term", 
          "attrs": {
            "name": "director", 
            "form": "verb-short"
          }
        }, 
        {
          "children": [
            "toim."
          ], 
          "name": "term", 
          "attrs": {
            "name": "editor", 
            "form": "verb-short"
          }
        }, 
        {
          "children": [
            "toim."
          ], 
          "name": "term", 
          "attrs": {
            "name": "editorial-director", 
            "form": "verb-short"
          }
        }, 
        {
          "children": [
            "kuv."
          ], 
          "name": "term", 
          "attrs": {
            "name": "illustrator", 
            "form": "verb-short"
          }
        }, 
        {
          "children": [
            "k\u00e4\u00e4nt."
          ], 
          "name": "term", 
          "attrs": {
            "name": "translator", 
            "form": "verb-short"
          }
        }, 
        {
          "children": [
            "toim. ja k\u00e4\u00e4nt."
          ], 
          "name": "term", 
          "attrs": {
            "name": "editortranslator", 
            "form": "verb-short"
          }
        }, 
        {
          "children": [
            "tammikuuta"
          ], 
          "name": "term", 
          "attrs": {
            "name": "month-01"
          }
        }, 
        {
          "children": [
            "helmikuuta"
          ], 
          "name": "term", 
          "attrs": {
            "name": "month-02"
          }
        }, 
        {
          "children": [
            "maaliskuuta"
          ], 
          "name": "term", 
          "attrs": {
            "name": "month-03"
          }
        }, 
        {
          "children": [
            "huhtikuuta"
          ], 
          "name": "term", 
          "attrs": {
            "name": "month-04"
          }
        }, 
        {
          "children": [
            "toukokuuta"
          ], 
          "name": "term", 
          "attrs": {
            "name": "month-05"
          }
        }, 
        {
          "children": [
            "kes\u00e4kuuta"
          ], 
          "name": "term", 
          "attrs": {
            "name": "month-06"
          }
        }, 
        {
          "children": [
            "hein\u00e4kuuta"
          ], 
          "name": "term", 
          "attrs": {
            "name": "month-07"
          }
        }, 
        {
          "children": [
            "elokuuta"
          ], 
          "name": "term", 
          "attrs": {
            "name": "month-08"
          }
        }, 
        {
          "children": [
            "syyskuuta"
          ], 
          "name": "term", 
          "attrs": {
            "name": "month-09"
          }
        }, 
        {
          "children": [
            "lokakuuta"
          ], 
          "name": "term", 
          "attrs": {
            "name": "month-10"
          }
        }, 
        {
          "children": [
            "marraskuuta"
          ], 
          "name": "term", 
          "attrs": {
            "name": "month-11"
          }
        }, 
        {
          "children": [
            "joulukuuta"
          ], 
          "name": "term", 
          "attrs": {
            "name": "month-12"
          }
        }, 
        {
          "children": [
            "tammi"
          ], 
          "name": "term", 
          "attrs": {
            "name": "month-01", 
            "form": "short"
          }
        }, 
        {
          "children": [
            "helmi"
          ], 
          "name": "term", 
          "attrs": {
            "name": "month-02", 
            "form": "short"
          }
        }, 
        {
          "children": [
            "maalis"
          ], 
          "name": "term", 
          "attrs": {
            "name": "month-03", 
            "form": "short"
          }
        }, 
        {
          "children": [
            "huhti"
          ], 
          "name": "term", 
          "attrs": {
            "name": "month-04", 
            "form": "short"
          }
        }, 
        {
          "children": [
            "touko"
          ], 
          "name": "term", 
          "attrs": {
            "name": "month-05", 
            "form": "short"
          }
        }, 
        {
          "children": [
            "kes\u00e4"
          ], 
          "name": "term", 
          "attrs": {
            "name": "month-06", 
            "form": "short"
          }
        }, 
        {
          "children": [
            "hein\u00e4"
          ], 
          "name": "term", 
          "attrs": {
            "name": "month-07", 
            "form": "short"
          }
        }, 
        {
          "children": [
            "elo"
          ], 
          "name": "term", 
          "attrs": {
            "name": "month-08", 
            "form": "short"
          }
        }, 
        {
          "children": [
            "syys"
          ], 
          "name": "term", 
          "attrs": {
            "name": "month-09", 
            "form": "short"
          }
        }, 
        {
          "children": [
            "loka"
          ], 
          "name": "term", 
          "attrs": {
            "name": "month-10", 
            "form": "short"
          }
        }, 
        {
          "children": [
            "marras"
          ], 
          "name": "term", 
          "attrs": {
            "name": "month-11", 
            "form": "short"
          }
        }, 
        {
          "children": [
            "joulu"
          ], 
          "name": "term", 
          "attrs": {
            "name": "month-12", 
            "form": "short"
          }
        }, 
        {
          "children": [
            "kev\u00e4t"
          ], 
          "name": "term", 
          "attrs": {
            "name": "season-01"
          }
        }, 
        {
          "children": [
            "kes\u00e4"
          ], 
          "name": "term", 
          "attrs": {
            "name": "season-02"
          }
        }, 
        {
          "children": [
            "syksy"
          ], 
          "name": "term", 
          "attrs": {
            "name": "season-03"
          }
        }, 
        {
          "children": [
            "talvi"
          ], 
          "name": "term", 
          "attrs": {
            "name": "season-04"
          }
        }
      ], 
      "name": "terms", 
      "attrs": {}
    }
  ], 
  "name": "locale", 
  "attrs": {
    "xmlns": "http://purl.org/net/xbiblio/csl", 
    "version": "1.0", 
    "xml:lang": "fi-FI"
  }
}